{
  "name": "scene3",
  "maxRecursionLevel": 6,
  "antiAliasingFactor": 1,
  "renderRefarctions": true,
  "renderReflections": true,
  "camera": {
    "cameraPosition": {
      "x": 0.0,
      "y": 2.0,
      "z": 6.0
    },
    "centerPoint": {
      "x": 0.0,
      "y": 1.800992561958002,
      "z": 4.009925619580022
    },
    "towardsVec": {
      "x": 0.0,
      "y": -0.09950371902099893,
      "z": -0.9950371902099893
    },
    "upVec": {
      "x": 0.0,
      "y": 0.9950371902099893,
      "z": -0.09950371902099893
    },
    "rightVec": {
      "x": 1.0,
      "y": -0.0,
      "z": 0.0
    },
    "viewAngle": 2.0,
    "distanceToPlain": 2.0,
    "resX": 200.0,
    "resY": 200.0,
    "pixelRatio": 0.0
  },
  "ambient": {
    "x": 1.0,
    "y": 1.0,
    "z": 1.0
  },
  "backgroundColor": {
    "x": 0.0,
    "y": 0.5,
    "z": 1.0
  },
  "lightSources": [
    {
      "CLASSNAME": "edu.cg.scene.lightSources.CutoffSpotlight",
      "DATA": {
        "direction": {
          "x": 0.0,
          "y": -1.0,
          "z": 0.0
        },
        "cutoffAngle": 45.0,
        "position": {
          "x": 4.0,
          "y": 4.0,
          "z": -3.0
        },
        "kq": 0.01,
        "kl": 0.1,
        "kc": 1.0,
        "intensity": {
          "x": 1.0,
          "y": 0.6,
          "z": 0.6
        }
      }
    },
    {
      "CLASSNAME": "edu.cg.scene.lightSources.CutoffSpotlight",
      "DATA": {
        "direction": {
          "x": 0.0,
          "y": -1.0,
          "z": 0.0
        },
        "cutoffAngle": 30.0,
        "position": {
          "x": -4.0,
          "y": 4.0,
          "z": -3.0
        },
        "kq": 0.01,
        "kl": 0.1,
        "kc": 1.0,
        "intensity": {
          "x": 0.6,
          "y": 1.0,
          "z": 0.6
        }
      }
    },
    {
      "CLASSNAME": "edu.cg.scene.lightSources.CutoffSpotlight",
      "DATA": {
        "direction": {
          "x": 0.0,
          "y": -1.0,
          "z": 0.0
        },
        "cutoffAngle": 30.0,
        "position": {
          "x": 0.0,
          "y": 4.0,
          "z": 0.0
        },
        "kq": 0.01,
        "kl": 0.1,
        "kc": 1.0,
        "intensity": {
          "x": 0.6,
          "y": 0.6,
          "z": 1.0
        }
      }
    },
    {
      "CLASSNAME": "edu.cg.scene.lightSources.DirectionalLight",
      "DATA": {
        "direction": {
          "x": 0.7071067811865475,
          "y": -0.7071067811865475,
          "z": 0.0
        },
        "intensity": {
          "x": 0.2,
          "y": 0.2,
          "z": 0.2
        }
      }
    }
  ],
  "surfaces": [
    {
      "shape": {
        "CLASSNAME": "edu.cg.scene.objects.Plain",
        "DATA": {
          "a": 0.0,
          "b": 1.0,
          "c": 0.0,
          "d": 1.0
        }
      },
      "material": {
        "Ka": {
          "x": 0.2,
          "y": 0.2,
          "z": 0.2
        },
        "Kd": {
          "x": 0.4,
          "y": 0.4,
          "z": 0.4
        },
        "Ks": {
          "x": 0.4,
          "y": 0.4,
          "z": 0.4
        },
        "reflectionIntensity": 0.2,
        "shininess": 10,
        "isTransparent": false,
        "refractionIntensity": 0.3,
        "refractionIndex": 1.5
      }
    },
    {
      "shape": {
        "CLASSNAME": "edu.cg.scene.objects.Sphere",
        "DATA": {
          "center": {
            "x": 0.0,
            "y": 0.0,
            "z": -0.0
          },
          "radius": 0.5
        }
      },
      "material": {
        "Ka": {
          "x": 0.3012659924391161,
          "y": 0.3643813233219954,
          "z": 0.28330665052234083
        },
        "Kd": {
          "x": 0.6025319848782322,
          "y": 0.7287626466439908,
          "z": 0.5666133010446817
        },
        "Ks": {
          "x": 0.42821719191947627,
          "y": 0.42821719191947627,
          "z": 0.42821719191947627
        },
        "reflectionIntensity": 0.0,
        "shininess": 10,
        "isTransparent": false,
        "refractionIntensity": 0.3,
        "refractionIndex": 1.5
      }
    },
    {
      "shape": {
        "CLASSNAME": "edu.cg.scene.objects.Sphere",
        "DATA": {
          "center": {
            "x": -1.0,
            "y": 0.0,
            "z": -1.0
          },
          "radius": 0.5
        }
      },
      "material": {
        "Ka": {
          "x": 0.47580495490090857,
          "y": 0.20467552787513849,
          "z": 0.20690535107767222
        },
        "Kd": {
          "x": 0.9516099098018171,
          "y": 0.40935105575027697,
          "z": 0.41381070215534443
        },
        "Ks": {
          "x": 0.25324047579764564,
          "y": 0.25324047579764564,
          "z": 0.25324047579764564
        },
        "reflectionIntensity": 0.0,
        "shininess": 10,
        "isTransparent": false,
        "refractionIntensity": 0.3,
        "refractionIndex": 1.5
      }
    },
    {
      "shape": {
        "CLASSNAME": "edu.cg.scene.objects.Sphere",
        "DATA": {
          "center": {
            "x": 0.0,
            "y": 0.0,
            "z": -1.0
          },
          "radius": 0.5
        }
      },
      "material": {
        "Ka": {
          "x": 0.2699714452895926,
          "y": 0.43508365472430605,
          "z": 0.29846007849358314
        },
        "Kd": {
          "x": 0.5399428905791852,
          "y": 0.8701673094486121,
          "z": 0.5969201569871663
        },
        "Ks": {
          "x": 0.7944101522274523,
          "y": 0.7944101522274523,
          "z": 0.7944101522274523
        },
        "reflectionIntensity": 0.0,
        "shininess": 10,
        "isTransparent": false,
        "refractionIntensity": 0.3,
        "refractionIndex": 1.5
      }
    },
    {
      "shape": {
        "CLASSNAME": "edu.cg.scene.objects.Sphere",
        "DATA": {
          "center": {
            "x": 1.0,
            "y": 0.0,
            "z": -1.0
          },
          "radius": 0.5
        }
      },
      "material": {
        "Ka": {
          "x": 0.2990644057317001,
          "y": 0.4881595065950394,
          "z": 0.08217061082522992
        },
        "Kd": {
          "x": 0.5981288114634002,
          "y": 0.9763190131900789,
          "z": 0.16434122165045983
        },
        "Ks": {
          "x": 1.0,
          "y": 1.0,
          "z": 1.0
        },
        "reflectionIntensity": 0.0,
        "shininess": 10,
        "isTransparent": false,
        "refractionIntensity": 0.3,
        "refractionIndex": 1.5
      }
    },
    {
      "shape": {
        "CLASSNAME": "edu.cg.scene.objects.Sphere",
        "DATA": {
          "center": {
            "x": -2.0,
            "y": 0.0,
            "z": -2.0
          },
          "radius": 0.5
        }
      },
      "material": {
        "Ka": {
          "x": 0.08413084658448139,
          "y": 0.28695638923636346,
          "z": 0.3102896769779163
        },
        "Kd": {
          "x": 0.16826169316896278,
          "y": 0.5739127784727269,
          "z": 0.6205793539558326
        },
        "Ks": {
          "x": 0.7115015520049341,
          "y": 0.7115015520049341,
          "z": 0.7115015520049341
        },
        "reflectionIntensity": 0.0,
        "shininess": 10,
        "isTransparent": false,
        "refractionIntensity": 0.3,
        "refractionIndex": 1.5
      }
    },
    {
      "shape": {
        "CLASSNAME": "edu.cg.scene.objects.Sphere",
        "DATA": {
          "center": {
            "x": -1.0,
            "y": 0.0,
            "z": -2.0
          },
          "radius": 0.5
        }
      },
      "material": {
        "Ka": {
          "x": 0.05387368555111727,
          "y": 0.3293820020782592,
          "z": 0.26887136232851594
        },
        "Kd": {
          "x": 0.10774737110223453,
          "y": 0.6587640041565184,
          "z": 0.5377427246570319
        },
        "Ks": {
          "x": 0.9844410153849656,
          "y": 0.9844410153849656,
          "z": 0.9844410153849656
        },
        "reflectionIntensity": 0.0,
        "shininess": 10,
        "isTransparent": false,
        "refractionIntensity": 0.3,
        "refractionIndex": 1.5
      }
    },
    {
      "shape": {
        "CLASSNAME": "edu.cg.scene.objects.Sphere",
        "DATA": {
          "center": {
            "x": 0.0,
            "y": 0.0,
            "z": -2.0
          },
          "radius": 0.5
        }
      },
      "material": {
        "Ka": {
          "x": 0.27046702140530443,
          "y": 0.4859627051602381,
          "z": 0.3196341378689926
        },
        "Kd": {
          "x": 0.5409340428106089,
          "y": 0.9719254103204762,
          "z": 0.6392682757379852
        },
        "Ks": {
          "x": 0.5364698922285559,
          "y": 0.5364698922285559,
          "z": 0.5364698922285559
        },
        "reflectionIntensity": 0.0,
        "shininess": 10,
        "isTransparent": false,
        "refractionIntensity": 0.3,
        "refractionIndex": 1.5
      }
    },
    {
      "shape": {
        "CLASSNAME": "edu.cg.scene.objects.Sphere",
        "DATA": {
          "center": {
            "x": 1.0,
            "y": 0.0,
            "z": -2.0
          },
          "radius": 0.5
        }
      },
      "material": {
        "Ka": {
          "x": 0.349982076202643,
          "y": 0.43484542438095575,
          "z": 0.1798913728234358
        },
        "Kd": {
          "x": 0.699964152405286,
          "y": 0.8696908487619115,
          "z": 0.3597827456468716
        },
        "Ks": {
          "x": 1.0,
          "y": 1.0,
          "z": 1.0
        },
        "reflectionIntensity": 0.0,
        "shininess": 10,
        "isTransparent": false,
        "refractionIntensity": 0.3,
        "refractionIndex": 1.5
      }
    },
    {
      "shape": {
        "CLASSNAME": "edu.cg.scene.objects.Sphere",
        "DATA": {
          "center": {
            "x": 2.0,
            "y": 0.0,
            "z": -2.0
          },
          "radius": 0.5
        }
      },
      "material": {
        "Ka": {
          "x": 0.17312675114625892,
          "y": 0.2828650939029984,
          "z": 0.06750275879679724
        },
        "Kd": {
          "x": 0.34625350229251783,
          "y": 0.5657301878059968,
          "z": 0.13500551759359447
        },
        "Ks": {
          "x": 0.5452712933941317,
          "y": 0.5452712933941317,
          "z": 0.5452712933941317
        },
        "reflectionIntensity": 1.0,
        "shininess": 10,
        "isTransparent": true,
        "refractionIntensity": 1.0,
        "refractionIndex": 1.9738209725717308
      }
    },
    {
      "shape": {
        "CLASSNAME": "edu.cg.scene.objects.Sphere",
        "DATA": {
          "center": {
            "x": -3.0,
            "y": 0.0,
            "z": -3.0
          },
          "radius": 0.5
        }
      },
      "material": {
        "Ka": {
          "x": 0.1,
          "y": 0.1,
          "z": 0.1
        },
        "Kd": {
          "x": 0.1,
          "y": 0.1,
          "z": 0.1
        },
        "Ks": {
          "x": 0.1,
          "y": 0.1,
          "z": 0.1
        },
        "reflectionIntensity": 0.95,
        "shininess": 14,
        "isTransparent": false,
        "refractionIntensity": 0.3,
        "refractionIndex": 1.5
      }
    },
    {
      "shape": {
        "CLASSNAME": "edu.cg.scene.objects.Sphere",
        "DATA": {
          "center": {
            "x": -2.0,
            "y": 0.0,
            "z": -3.0
          },
          "radius": 0.5
        }
      },
      "material": {
        "Ka": {
          "x": 0.2615949762975206,
          "y": 0.28136857495981593,
          "z": 0.08357882330578065
        },
        "Kd": {
          "x": 0.5231899525950412,
          "y": 0.5627371499196319,
          "z": 0.1671576466115613
        },
        "Ks": {
          "x": 0.8331706542135483,
          "y": 0.8331706542135483,
          "z": 0.8331706542135483
        },
        "reflectionIntensity": 0.0,
        "shininess": 10,
        "isTransparent": false,
        "refractionIntensity": 0.3,
        "refractionIndex": 1.5
      }
    },
    {
      "shape": {
        "CLASSNAME": "edu.cg.scene.objects.Sphere",
        "DATA": {
          "center": {
            "x": -1.0,
            "y": 0.0,
            "z": -3.0
          },
          "radius": 0.5
        }
      },
      "material": {
        "Ka": {
          "x": 0.1581930129321406,
          "y": 0.175324745655152,
          "z": 0.005596643597914008
        },
        "Kd": {
          "x": 0.3163860258642812,
          "y": 0.350649491310304,
          "z": 0.011193287195828017
        },
        "Ks": {
          "x": 0.33224907033572293,
          "y": 0.33224907033572293,
          "z": 0.33224907033572293
        },
        "reflectionIntensity": 0.9609715000023958,
        "shininess": 10,
        "isTransparent": false,
        "refractionIntensity": 0.3,
        "refractionIndex": 1.5
      }
    },
    {
      "shape": {
        "CLASSNAME": "edu.cg.scene.objects.Sphere",
        "DATA": {
          "center": {
            "x": 0.0,
            "y": 0.0,
            "z": -3.0
          },
          "radius": 0.5
        }
      },
      "material": {
        "Ka": {
          "x": 0.4963251169287326,
          "y": 0.07559021899648166,
          "z": 0.20076761015879835
        },
        "Kd": {
          "x": 0.9926502338574652,
          "y": 0.15118043799296332,
          "z": 0.4015352203175967
        },
        "Ks": {
          "x": 0.2602022706185899,
          "y": 0.2602022706185899,
          "z": 0.2602022706185899
        },
        "reflectionIntensity": 0.0,
        "shininess": 10,
        "isTransparent": true,
        "refractionIntensity": 1.0,
        "refractionIndex": 1.3908796079163732
      }
    },
    {
      "shape": {
        "CLASSNAME": "edu.cg.scene.objects.Sphere",
        "DATA": {
          "center": {
            "x": 1.0,
            "y": 0.0,
            "z": -3.0
          },
          "radius": 0.5
        }
      },
      "material": {
        "Ka": {
          "x": 0.2687441205678422,
          "y": 0.07398636245309614,
          "z": 0.2669587368040793
        },
        "Kd": {
          "x": 0.5374882411356844,
          "y": 0.1479727249061923,
          "z": 0.5339174736081586
        },
        "Ks": {
          "x": 1.0,
          "y": 1.0,
          "z": 1.0
        },
        "reflectionIntensity": 0.0,
        "shininess": 10,
        "isTransparent": false,
        "refractionIntensity": 0.3,
        "refractionIndex": 1.5
      }
    },
    {
      "shape": {
        "CLASSNAME": "edu.cg.scene.objects.Sphere",
        "DATA": {
          "center": {
            "x": 2.0,
            "y": 0.0,
            "z": -3.0
          },
          "radius": 0.5
        }
      },
      "material": {
        "Ka": {
          "x": 0.1,
          "y": 0.1,
          "z": 0.1
        },
        "Kd": {
          "x": 0.1,
          "y": 0.1,
          "z": 0.1
        },
        "Ks": {
          "x": 0.1,
          "y": 0.1,
          "z": 0.1
        },
        "reflectionIntensity": 0.95,
        "shininess": 9,
        "isTransparent": false,
        "refractionIntensity": 0.3,
        "refractionIndex": 1.5
      }
    },
    {
      "shape": {
        "CLASSNAME": "edu.cg.scene.objects.Sphere",
        "DATA": {
          "center": {
            "x": 3.0,
            "y": 0.0,
            "z": -3.0
          },
          "radius": 0.5
        }
      },
      "material": {
        "Ka": {
          "x": 0.3300578065362078,
          "y": 0.4316507889540499,
          "z": 0.28934640655712607
        },
        "Kd": {
          "x": 0.6601156130724156,
          "y": 0.8633015779080998,
          "z": 0.5786928131142521
        },
        "Ks": {
          "x": 0.7222066612894812,
          "y": 0.7222066612894812,
          "z": 0.7222066612894812
        },
        "reflectionIntensity": 0.0,
        "shininess": 10,
        "isTransparent": false,
        "refractionIntensity": 0.3,
        "refractionIndex": 1.5
      }
    }
  ]
}