{
  "name": "scene3",
  "maxRecursionLevel": 6,
  "antiAliasingFactor": 1,
  "renderRefractions": true,
  "renderReflections": true,
  "camera": {
    "cameraPosition": {
      "x": 0.0,
      "y": 2.0,
      "z": 6.0
    },
    "plainCenter": {
      "x": 0.0,
      "y": 1.800992561958002,
      "z": 4.009925619580022
    },
    "Vup": {
      "x": 0.0,
      "y": 0.9950371902099893,
      "z": -0.09950371902099893
    },
    "Vright": {
      "x": 1.0,
      "y": -0.0,
      "z": 0.0
    },
    "Vtowards": {
      "x": 0.0,
      "y": -0.09950371902099893,
      "z": -0.9950371902099893
    },
    "Rx": 200,
    "Ry": 200,
    "distanceToPlain": 2.0,
    "imageWidth": 3.9999999999999996,
    "imageHeight": 3.9999999999999996,
    "pixelWidth": 0.019999999999999997,
    "viewAngle": 90.0
  },
  "ambient": {
    "x": 1.0,
    "y": 1.0,
    "z": 1.0
  },
  "backgroundColor": {
    "x": 0.0,
    "y": 0.5,
    "z": 1.0
  },
  "lightSources": [
    {
      "CLASSNAME": "edu.cg.scene.lightSources.CutoffSpotlight",
      "DATA": {
        "direction": {
          "x": 0.0,
          "y": -1.0,
          "z": 0.0
        },
        "cutoffAngle": 45.0,
        "position": {
          "x": 4.0,
          "y": 4.0,
          "z": -3.0
        },
        "kq": 0.01,
        "kl": 0.1,
        "kc": 1.0,
        "intensity": {
          "x": 1.0,
          "y": 0.6,
          "z": 0.6
        }
      }
    },
    {
      "CLASSNAME": "edu.cg.scene.lightSources.CutoffSpotlight",
      "DATA": {
        "direction": {
          "x": 0.0,
          "y": -1.0,
          "z": 0.0
        },
        "cutoffAngle": 30.0,
        "position": {
          "x": -4.0,
          "y": 4.0,
          "z": -3.0
        },
        "kq": 0.01,
        "kl": 0.1,
        "kc": 1.0,
        "intensity": {
          "x": 0.6,
          "y": 1.0,
          "z": 0.6
        }
      }
    },
    {
      "CLASSNAME": "edu.cg.scene.lightSources.CutoffSpotlight",
      "DATA": {
        "direction": {
          "x": 0.0,
          "y": -1.0,
          "z": 0.0
        },
        "cutoffAngle": 30.0,
        "position": {
          "x": 0.0,
          "y": 4.0,
          "z": 0.0
        },
        "kq": 0.01,
        "kl": 0.1,
        "kc": 1.0,
        "intensity": {
          "x": 0.6,
          "y": 0.6,
          "z": 1.0
        }
      }
    },
    {
      "CLASSNAME": "edu.cg.scene.lightSources.DirectionalLight",
      "DATA": {
        "direction": {
          "x": 0.7071067811865475,
          "y": -0.7071067811865475,
          "z": 0.0
        },
        "intensity": {
          "x": 0.2,
          "y": 0.2,
          "z": 0.2
        }
      }
    }
  ],
  "surfaces": [
    {
      "shape": {
        "CLASSNAME": "edu.cg.scene.objects.Plain",
        "DATA": {
          "a": 0.0,
          "b": 1.0,
          "c": 0.0,
          "d": 1.0
        }
      },
      "material": {
        "Ka": {
          "x": 0.2,
          "y": 0.2,
          "z": 0.2
        },
        "Kd": {
          "x": 0.4,
          "y": 0.4,
          "z": 0.4
        },
        "Ks": {
          "x": 0.4,
          "y": 0.4,
          "z": 0.4
        },
        "reflectionIntensity": 0.2,
        "shininess": 10,
        "isTransparent": false,
        "refractionIntensity": 0.3,
        "refractionIndex": 1.5
      }
    },
    {
      "shape": {
        "CLASSNAME": "edu.cg.scene.objects.Sphere",
        "DATA": {
          "center": {
            "x": 0.0,
            "y": 0.0,
            "z": -0.0
          },
          "radius": 0.5
        }
      },
      "material": {
        "Ka": {
          "x": 0.3441041430990279,
          "y": 0.21559557139864377,
          "z": 0.13174183589684874
        },
        "Kd": {
          "x": 0.6882082861980559,
          "y": 0.43119114279728754,
          "z": 0.26348367179369747
        },
        "Ks": {
          "x": 1.0,
          "y": 1.0,
          "z": 1.0
        },
        "reflectionIntensity": 0.5646669008912943,
        "shininess": 10,
        "isTransparent": false,
        "refractionIntensity": 0.3,
        "refractionIndex": 1.5
      }
    },
    {
      "shape": {
        "CLASSNAME": "edu.cg.scene.objects.Sphere",
        "DATA": {
          "center": {
            "x": -1.0,
            "y": 0.0,
            "z": -1.0
          },
          "radius": 0.5
        }
      },
      "material": {
        "Ka": {
          "x": 0.12697473261032732,
          "y": 0.29409437913158737,
          "z": 0.21078089406212253
        },
        "Kd": {
          "x": 0.25394946522065465,
          "y": 0.5881887582631747,
          "z": 0.42156178812424505
        },
        "Ks": {
          "x": 0.45608681271736984,
          "y": 0.45608681271736984,
          "z": 0.45608681271736984
        },
        "reflectionIntensity": 0.0,
        "shininess": 10,
        "isTransparent": false,
        "refractionIntensity": 0.3,
        "refractionIndex": 1.5
      }
    },
    {
      "shape": {
        "CLASSNAME": "edu.cg.scene.objects.Sphere",
        "DATA": {
          "center": {
            "x": 0.0,
            "y": 0.0,
            "z": -1.0
          },
          "radius": 0.5
        }
      },
      "material": {
        "Ka": {
          "x": 0.12001982683154405,
          "y": 0.1802072425617855,
          "z": 0.13765430628367364
        },
        "Kd": {
          "x": 0.2400396536630881,
          "y": 0.360414485123571,
          "z": 0.2753086125673473
        },
        "Ks": {
          "x": 0.2905606640957564,
          "y": 0.2905606640957564,
          "z": 0.2905606640957564
        },
        "reflectionIntensity": 0.0,
        "shininess": 10,
        "isTransparent": false,
        "refractionIntensity": 0.3,
        "refractionIndex": 1.5
      }
    },
    {
      "shape": {
        "CLASSNAME": "edu.cg.scene.objects.Sphere",
        "DATA": {
          "center": {
            "x": 1.0,
            "y": 0.0,
            "z": -1.0
          },
          "radius": 0.5
        }
      },
      "material": {
        "Ka": {
          "x": 0.15821194629730262,
          "y": 0.3927364333180952,
          "z": 0.07260244340465893
        },
        "Kd": {
          "x": 0.31642389259460524,
          "y": 0.7854728666361904,
          "z": 0.14520488680931787
        },
        "Ks": {
          "x": 0.8825934700183987,
          "y": 0.8825934700183987,
          "z": 0.8825934700183987
        },
        "reflectionIntensity": 0.0,
        "shininess": 10,
        "isTransparent": false,
        "refractionIntensity": 0.3,
        "refractionIndex": 1.5
      }
    },
    {
      "shape": {
        "CLASSNAME": "edu.cg.scene.objects.Sphere",
        "DATA": {
          "center": {
            "x": -2.0,
            "y": 0.0,
            "z": -2.0
          },
          "radius": 0.5
        }
      },
      "material": {
        "Ka": {
          "x": 0.4665602807804465,
          "y": 0.11613140774843234,
          "z": 0.11423252871929507
        },
        "Kd": {
          "x": 0.933120561560893,
          "y": 0.23226281549686467,
          "z": 0.22846505743859014
        },
        "Ks": {
          "x": 1.0,
          "y": 1.0,
          "z": 1.0
        },
        "reflectionIntensity": 0.0,
        "shininess": 10,
        "isTransparent": false,
        "refractionIntensity": 0.3,
        "refractionIndex": 1.5
      }
    },
    {
      "shape": {
        "CLASSNAME": "edu.cg.scene.objects.Sphere",
        "DATA": {
          "center": {
            "x": -1.0,
            "y": 0.0,
            "z": -2.0
          },
          "radius": 0.5
        }
      },
      "material": {
        "Ka": {
          "x": 0.40812279525744194,
          "y": 0.04412391271398025,
          "z": 0.08277256544944189
        },
        "Kd": {
          "x": 0.8162455905148839,
          "y": 0.0882478254279605,
          "z": 0.16554513089888379
        },
        "Ks": {
          "x": 0.8509242988458172,
          "y": 0.8509242988458172,
          "z": 0.8509242988458172
        },
        "reflectionIntensity": 0.0,
        "shininess": 10,
        "isTransparent": false,
        "refractionIntensity": 0.3,
        "refractionIndex": 1.5
      }
    },
    {
      "shape": {
        "CLASSNAME": "edu.cg.scene.objects.Sphere",
        "DATA": {
          "center": {
            "x": 0.0,
            "y": 0.0,
            "z": -2.0
          },
          "radius": 0.5
        }
      },
      "material": {
        "Ka": {
          "x": 0.3614118384506749,
          "y": 0.16576778621057836,
          "z": 0.31621628669013807
        },
        "Kd": {
          "x": 0.7228236769013499,
          "y": 0.3315355724211567,
          "z": 0.6324325733802761
        },
        "Ks": {
          "x": 0.3293776503405663,
          "y": 0.3293776503405663,
          "z": 0.3293776503405663
        },
        "reflectionIntensity": 0.0,
        "shininess": 10,
        "isTransparent": false,
        "refractionIntensity": 0.3,
        "refractionIndex": 1.5
      }
    },
    {
      "shape": {
        "CLASSNAME": "edu.cg.scene.objects.Sphere",
        "DATA": {
          "center": {
            "x": 1.0,
            "y": 0.0,
            "z": -2.0
          },
          "radius": 0.5
        }
      },
      "material": {
        "Ka": {
          "x": 0.10845041251581206,
          "y": 0.43542043570968714,
          "z": 0.17096642840361947
        },
        "Kd": {
          "x": 0.2169008250316241,
          "y": 0.8708408714193743,
          "z": 0.34193285680723895
        },
        "Ks": {
          "x": 0.6508898999457341,
          "y": 0.6508898999457341,
          "z": 0.6508898999457341
        },
        "reflectionIntensity": 0.0,
        "shininess": 10,
        "isTransparent": false,
        "refractionIntensity": 0.3,
        "refractionIndex": 1.5
      }
    },
    {
      "shape": {
        "CLASSNAME": "edu.cg.scene.objects.Sphere",
        "DATA": {
          "center": {
            "x": 2.0,
            "y": 0.0,
            "z": -2.0
          },
          "radius": 0.5
        }
      },
      "material": {
        "Ka": {
          "x": 0.36824472424671695,
          "y": 0.4770566027170577,
          "z": 0.01799187924474821
        },
        "Kd": {
          "x": 0.7364894484934339,
          "y": 0.9541132054341154,
          "z": 0.03598375848949642
        },
        "Ks": {
          "x": 1.0,
          "y": 1.0,
          "z": 1.0
        },
        "reflectionIntensity": 0.0,
        "shininess": 10,
        "isTransparent": true,
        "refractionIntensity": 0.266666532019718,
        "refractionIndex": 1.4871832613906701
      }
    },
    {
      "shape": {
        "CLASSNAME": "edu.cg.scene.objects.Sphere",
        "DATA": {
          "center": {
            "x": -3.0,
            "y": 0.0,
            "z": -3.0
          },
          "radius": 0.5
        }
      },
      "material": {
        "Ka": {
          "x": 0.09830503881104069,
          "y": 0.15051441187503495,
          "z": 0.3522330113110111
        },
        "Kd": {
          "x": 0.19661007762208138,
          "y": 0.3010288237500699,
          "z": 0.7044660226220222
        },
        "Ks": {
          "x": 0.5902020339363235,
          "y": 0.5902020339363235,
          "z": 0.5902020339363235
        },
        "reflectionIntensity": 0.0,
        "shininess": 10,
        "isTransparent": false,
        "refractionIntensity": 0.3,
        "refractionIndex": 1.5
      }
    },
    {
      "shape": {
        "CLASSNAME": "edu.cg.scene.objects.Sphere",
        "DATA": {
          "center": {
            "x": -2.0,
            "y": 0.0,
            "z": -3.0
          },
          "radius": 0.5
        }
      },
      "material": {
        "Ka": {
          "x": 0.014598623427566071,
          "y": 0.14424052347115063,
          "z": 0.302250391382829
        },
        "Kd": {
          "x": 0.029197246855132142,
          "y": 0.28848104694230126,
          "z": 0.604500782765658
        },
        "Ks": {
          "x": 1.0,
          "y": 1.0,
          "z": 1.0
        },
        "reflectionIntensity": 1.0,
        "shininess": 10,
        "isTransparent": false,
        "refractionIntensity": 0.3,
        "refractionIndex": 1.5
      }
    },
    {
      "shape": {
        "CLASSNAME": "edu.cg.scene.objects.Sphere",
        "DATA": {
          "center": {
            "x": -1.0,
            "y": 0.0,
            "z": -3.0
          },
          "radius": 0.5
        }
      },
      "material": {
        "Ka": {
          "x": 0.3361541534150456,
          "y": 0.09217722468425327,
          "z": 0.10305766907985475
        },
        "Kd": {
          "x": 0.6723083068300912,
          "y": 0.18435444936850653,
          "z": 0.2061153381597095
        },
        "Ks": {
          "x": 0.5873623114637018,
          "y": 0.5873623114637018,
          "z": 0.5873623114637018
        },
        "reflectionIntensity": 0.0,
        "shininess": 10,
        "isTransparent": false,
        "refractionIntensity": 0.3,
        "refractionIndex": 1.5
      }
    },
    {
      "shape": {
        "CLASSNAME": "edu.cg.scene.objects.Sphere",
        "DATA": {
          "center": {
            "x": 0.0,
            "y": 0.0,
            "z": -3.0
          },
          "radius": 0.5
        }
      },
      "material": {
        "Ka": {
          "x": 0.21288572018989443,
          "y": 0.12309821072812777,
          "z": 0.22430963274030458
        },
        "Kd": {
          "x": 0.42577144037978887,
          "y": 0.24619642145625553,
          "z": 0.44861926548060915
        },
        "Ks": {
          "x": 0.37957661302995205,
          "y": 0.37957661302995205,
          "z": 0.37957661302995205
        },
        "reflectionIntensity": 0.7517035923719316,
        "shininess": 10,
        "isTransparent": false,
        "refractionIntensity": 0.3,
        "refractionIndex": 1.5
      }
    },
    {
      "shape": {
        "CLASSNAME": "edu.cg.scene.objects.Sphere",
        "DATA": {
          "center": {
            "x": 1.0,
            "y": 0.0,
            "z": -3.0
          },
          "radius": 0.5
        }
      },
      "material": {
        "Ka": {
          "x": 0.16978749496482592,
          "y": 0.4272595673855076,
          "z": 0.3268952403929453
        },
        "Kd": {
          "x": 0.33957498992965185,
          "y": 0.8545191347710152,
          "z": 0.6537904807858906
        },
        "Ks": {
          "x": 1.0,
          "y": 1.0,
          "z": 1.0
        },
        "reflectionIntensity": 0.0,
        "shininess": 10,
        "isTransparent": false,
        "refractionIntensity": 0.3,
        "refractionIndex": 1.5
      }
    },
    {
      "shape": {
        "CLASSNAME": "edu.cg.scene.objects.Sphere",
        "DATA": {
          "center": {
            "x": 2.0,
            "y": 0.0,
            "z": -3.0
          },
          "radius": 0.5
        }
      },
      "material": {
        "Ka": {
          "x": 0.09653516176356475,
          "y": 0.14439712685871353,
          "z": 0.29005594504779625
        },
        "Kd": {
          "x": 0.1930703235271295,
          "y": 0.28879425371742706,
          "z": 0.5801118900955925
        },
        "Ks": {
          "x": 0.9527854351187036,
          "y": 0.9527854351187036,
          "z": 0.9527854351187036
        },
        "reflectionIntensity": 1.0,
        "shininess": 10,
        "isTransparent": false,
        "refractionIntensity": 0.3,
        "refractionIndex": 1.5
      }
    },
    {
      "shape": {
        "CLASSNAME": "edu.cg.scene.objects.Sphere",
        "DATA": {
          "center": {
            "x": 3.0,
            "y": 0.0,
            "z": -3.0
          },
          "radius": 0.5
        }
      },
      "material": {
        "Ka": {
          "x": 0.1,
          "y": 0.1,
          "z": 0.1
        },
        "Kd": {
          "x": 0.1,
          "y": 0.1,
          "z": 0.1
        },
        "Ks": {
          "x": 0.1,
          "y": 0.1,
          "z": 0.1
        },
        "reflectionIntensity": 0.95,
        "shininess": 7,
        "isTransparent": false,
        "refractionIntensity": 0.3,
        "refractionIndex": 1.5
      }
    }
  ]
}