{
  "name": "scene2",
  "maxRecursionLevel": 6,
  "antiAliasingFactor": 1,
  "renderRefarctions": true,
  "renderReflections": true,
  "camera": {
    "cameraPosition": {
      "x": 0.0,
      "y": 2.0,
      "z": 6.0
    },
    "plainCenter": {
      "x": 0.0,
      "y": 1.800992561958002,
      "z": 4.009925619580022
    },
    "Vup": {
      "x": 0.0,
      "y": 0.9950371902099893,
      "z": -0.09950371902099893
    },
    "Vright": {
      "x": 1.0,
      "y": -0.0,
      "z": 0.0
    },
    "Vtowards": {
      "x": 0.0,
      "y": -0.09950371902099893,
      "z": -0.9950371902099893
    },
    "Rx": 200,
    "Ry": 200,
    "distanceToPlain": 2.0,
    "imageWidth": 3.9999999999999996,
    "imageHeight": 3.9999999999999996,
    "pixelWidth": 0.019999999999999997,
    "viewAngle": 90.0
  },
  "ambient": {
    "x": 0.4,
    "y": 0.4,
    "z": 0.4
  },
  "backgroundColor": {
    "x": 0.0,
    "y": 0.5,
    "z": 1.0
  },
  "lightSources": [
    {
      "CLASSNAME": "edu.cg.scene.lightSources.DirectionalLight",
      "DATA": {
        "direction": {
          "x": 0.7071067811865475,
          "y": -0.7071067811865475,
          "z": 0.0
        },
        "intensity": {
          "x": 0.7,
          "y": 0.7,
          "z": 0.7
        }
      }
    }
  ],
  "surfaces": [
    {
      "shape": {
        "CLASSNAME": "edu.cg.scene.objects.Plain",
        "DATA": {
          "a": 0.0,
          "b": 1.0,
          "c": 0.0,
          "d": 1.0
        }
      },
      "material": {
        "Ka": {
          "x": 0.2,
          "y": 0.2,
          "z": 0.2
        },
        "Kd": {
          "x": 0.4,
          "y": 0.4,
          "z": 0.4
        },
        "Ks": {
          "x": 0.4,
          "y": 0.4,
          "z": 0.4
        },
        "reflectionIntensity": 0.2,
        "shininess": 10,
        "isTransparent": false,
        "refractionIntensity": 0.3,
        "refractionIndex": 1.5
      }
    },
    {
      "shape": {
        "CLASSNAME": "edu.cg.scene.objects.Sphere",
        "DATA": {
          "center": {
            "x": 0.0,
            "y": 0.0,
            "z": -0.0
          },
          "radius": 0.5
        }
      },
      "material": {
        "Ka": {
          "x": 0.18794666616706474,
          "y": 0.4401845558778143,
          "z": 0.22118703903183579
        },
        "Kd": {
          "x": 0.37589333233412947,
          "y": 0.8803691117556286,
          "z": 0.44237407806367157
        },
        "Ks": {
          "x": 0.7244807679674178,
          "y": 0.7244807679674178,
          "z": 0.7244807679674178
        },
        "reflectionIntensity": 0.9910697168564576,
        "shininess": 10,
        "isTransparent": true,
        "refractionIntensity": 0.5305079412225173,
        "refractionIndex": 2.2143685928803127
      }
    },
    {
      "shape": {
        "CLASSNAME": "edu.cg.scene.objects.Sphere",
        "DATA": {
          "center": {
            "x": -1.0,
            "y": 0.0,
            "z": -1.0
          },
          "radius": 0.5
        }
      },
      "material": {
        "Ka": {
          "x": 0.2805848781638747,
          "y": 0.07567064107594512,
          "z": 0.4480806801565708
        },
        "Kd": {
          "x": 0.5611697563277493,
          "y": 0.15134128215189024,
          "z": 0.8961613603131416
        },
        "Ks": {
          "x": 0.34168800533122756,
          "y": 0.34168800533122756,
          "z": 0.34168800533122756
        },
        "reflectionIntensity": 0.0,
        "shininess": 10,
        "isTransparent": false,
        "refractionIntensity": 0.3,
        "refractionIndex": 1.5
      }
    },
    {
      "shape": {
        "CLASSNAME": "edu.cg.scene.objects.Sphere",
        "DATA": {
          "center": {
            "x": 0.0,
            "y": 0.0,
            "z": -1.0
          },
          "radius": 0.5
        }
      },
      "material": {
        "Ka": {
          "x": 0.1,
          "y": 0.1,
          "z": 0.1
        },
        "Kd": {
          "x": 0.1,
          "y": 0.1,
          "z": 0.1
        },
        "Ks": {
          "x": 0.1,
          "y": 0.1,
          "z": 0.1
        },
        "reflectionIntensity": 0.95,
        "shininess": 3,
        "isTransparent": false,
        "refractionIntensity": 0.3,
        "refractionIndex": 1.5
      }
    },
    {
      "shape": {
        "CLASSNAME": "edu.cg.scene.objects.Sphere",
        "DATA": {
          "center": {
            "x": 1.0,
            "y": 0.0,
            "z": -1.0
          },
          "radius": 0.5
        }
      },
      "material": {
        "Ka": {
          "x": 0.11789027122857931,
          "y": 0.4290019658052362,
          "z": 0.3312316969527996
        },
        "Kd": {
          "x": 0.23578054245715863,
          "y": 0.8580039316104724,
          "z": 0.6624633939055992
        },
        "Ks": {
          "x": 0.476837883994892,
          "y": 0.476837883994892,
          "z": 0.476837883994892
        },
        "reflectionIntensity": 0.7396682233271831,
        "shininess": 10,
        "isTransparent": true,
        "refractionIntensity": 0.4690837811748063,
        "refractionIndex": 2.1047835146500047
      }
    },
    {
      "shape": {
        "CLASSNAME": "edu.cg.scene.objects.Sphere",
        "DATA": {
          "center": {
            "x": -2.0,
            "y": 0.0,
            "z": -2.0
          },
          "radius": 0.5
        }
      },
      "material": {
        "Ka": {
          "x": 0.29516738691652233,
          "y": 0.4425506889795572,
          "z": 0.12935499094202163
        },
        "Kd": {
          "x": 0.5903347738330447,
          "y": 0.8851013779591144,
          "z": 0.25870998188404326
        },
        "Ks": {
          "x": 0.9672948425085953,
          "y": 0.9672948425085953,
          "z": 0.9672948425085953
        },
        "reflectionIntensity": 0.0,
        "shininess": 10,
        "isTransparent": false,
        "refractionIntensity": 0.3,
        "refractionIndex": 1.5
      }
    },
    {
      "shape": {
        "CLASSNAME": "edu.cg.scene.objects.Sphere",
        "DATA": {
          "center": {
            "x": -1.0,
            "y": 0.0,
            "z": -2.0
          },
          "radius": 0.5
        }
      },
      "material": {
        "Ka": {
          "x": 0.1,
          "y": 0.1,
          "z": 0.1
        },
        "Kd": {
          "x": 0.1,
          "y": 0.1,
          "z": 0.1
        },
        "Ks": {
          "x": 0.1,
          "y": 0.1,
          "z": 0.1
        },
        "reflectionIntensity": 0.95,
        "shininess": 9,
        "isTransparent": false,
        "refractionIntensity": 0.3,
        "refractionIndex": 1.5
      }
    },
    {
      "shape": {
        "CLASSNAME": "edu.cg.scene.objects.Sphere",
        "DATA": {
          "center": {
            "x": 0.0,
            "y": 0.0,
            "z": -2.0
          },
          "radius": 0.5
        }
      },
      "material": {
        "Ka": {
          "x": 0.1934570079628467,
          "y": 0.091533131739364,
          "z": 0.12966547092377273
        },
        "Kd": {
          "x": 0.3869140159256934,
          "y": 0.183066263478728,
          "z": 0.25933094184754546
        },
        "Ks": {
          "x": 0.8350681659579874,
          "y": 0.8350681659579874,
          "z": 0.8350681659579874
        },
        "reflectionIntensity": 0.0,
        "shininess": 10,
        "isTransparent": true,
        "refractionIntensity": 0.49999034508208573,
        "refractionIndex": 2.1054098967621875
      }
    },
    {
      "shape": {
        "CLASSNAME": "edu.cg.scene.objects.Sphere",
        "DATA": {
          "center": {
            "x": 1.0,
            "y": 0.0,
            "z": -2.0
          },
          "radius": 0.5
        }
      },
      "material": {
        "Ka": {
          "x": 0.10117020248730701,
          "y": 0.43257318530258126,
          "z": 0.07308999577143666
        },
        "Kd": {
          "x": 0.20234040497461403,
          "y": 0.8651463706051625,
          "z": 0.1461799915428733
        },
        "Ks": {
          "x": 1.0,
          "y": 1.0,
          "z": 1.0
        },
        "reflectionIntensity": 0.0,
        "shininess": 10,
        "isTransparent": false,
        "refractionIntensity": 0.3,
        "refractionIndex": 1.5
      }
    },
    {
      "shape": {
        "CLASSNAME": "edu.cg.scene.objects.Sphere",
        "DATA": {
          "center": {
            "x": 2.0,
            "y": 0.0,
            "z": -2.0
          },
          "radius": 0.5
        }
      },
      "material": {
        "Ka": {
          "x": 0.024154316383461882,
          "y": 0.2814477092643313,
          "z": 0.33167629248991376
        },
        "Kd": {
          "x": 0.048308632766923765,
          "y": 0.5628954185286626,
          "z": 0.6633525849798275
        },
        "Ks": {
          "x": 0.9919044119388797,
          "y": 0.9919044119388797,
          "z": 0.9919044119388797
        },
        "reflectionIntensity": 0.26379600491083033,
        "shininess": 10,
        "isTransparent": false,
        "refractionIntensity": 0.3,
        "refractionIndex": 1.5
      }
    },
    {
      "shape": {
        "CLASSNAME": "edu.cg.scene.objects.Sphere",
        "DATA": {
          "center": {
            "x": -3.0,
            "y": 0.0,
            "z": -3.0
          },
          "radius": 0.5
        }
      },
      "material": {
        "Ka": {
          "x": 0.28456262961961665,
          "y": 0.40860569730497537,
          "z": 0.3232607458168666
        },
        "Kd": {
          "x": 0.5691252592392333,
          "y": 0.8172113946099507,
          "z": 0.6465214916337332
        },
        "Ks": {
          "x": 0.8280510984822377,
          "y": 0.8280510984822377,
          "z": 0.8280510984822377
        },
        "reflectionIntensity": 0.0,
        "shininess": 10,
        "isTransparent": false,
        "refractionIntensity": 0.3,
        "refractionIndex": 1.5
      }
    },
    {
      "shape": {
        "CLASSNAME": "edu.cg.scene.objects.Sphere",
        "DATA": {
          "center": {
            "x": -2.0,
            "y": 0.0,
            "z": -3.0
          },
          "radius": 0.5
        }
      },
      "material": {
        "Ka": {
          "x": 0.2236699291348781,
          "y": 0.3660467050026921,
          "z": 0.26602151822239595
        },
        "Kd": {
          "x": 0.4473398582697562,
          "y": 0.7320934100053842,
          "z": 0.5320430364447919
        },
        "Ks": {
          "x": 0.6028937294935118,
          "y": 0.6028937294935118,
          "z": 0.6028937294935118
        },
        "reflectionIntensity": 0.9102415983307961,
        "shininess": 10,
        "isTransparent": false,
        "refractionIntensity": 0.3,
        "refractionIndex": 1.5
      }
    },
    {
      "shape": {
        "CLASSNAME": "edu.cg.scene.objects.Sphere",
        "DATA": {
          "center": {
            "x": -1.0,
            "y": 0.0,
            "z": -3.0
          },
          "radius": 0.5
        }
      },
      "material": {
        "Ka": {
          "x": 0.405821852365938,
          "y": 0.4536704185204716,
          "z": 0.10019219716308547
        },
        "Kd": {
          "x": 0.811643704731876,
          "y": 0.9073408370409431,
          "z": 0.20038439432617094
        },
        "Ks": {
          "x": 0.4035939103704188,
          "y": 0.4035939103704188,
          "z": 0.4035939103704188
        },
        "reflectionIntensity": 0.0,
        "shininess": 10,
        "isTransparent": false,
        "refractionIntensity": 0.3,
        "refractionIndex": 1.5
      }
    },
    {
      "shape": {
        "CLASSNAME": "edu.cg.scene.objects.Sphere",
        "DATA": {
          "center": {
            "x": 0.0,
            "y": 0.0,
            "z": -3.0
          },
          "radius": 0.5
        }
      },
      "material": {
        "Ka": {
          "x": 0.2339501483905453,
          "y": 0.29775108567002,
          "z": 0.17726662313174135
        },
        "Kd": {
          "x": 0.4679002967810906,
          "y": 0.59550217134004,
          "z": 0.3545332462634827
        },
        "Ks": {
          "x": 0.4998895056901299,
          "y": 0.4998895056901299,
          "z": 0.4998895056901299
        },
        "reflectionIntensity": 0.0,
        "shininess": 10,
        "isTransparent": false,
        "refractionIntensity": 0.3,
        "refractionIndex": 1.5
      }
    },
    {
      "shape": {
        "CLASSNAME": "edu.cg.scene.objects.Sphere",
        "DATA": {
          "center": {
            "x": 1.0,
            "y": 0.0,
            "z": -3.0
          },
          "radius": 0.5
        }
      },
      "material": {
        "Ka": {
          "x": 0.026660558604061968,
          "y": 0.42865581577403455,
          "z": 0.35532709830540216
        },
        "Kd": {
          "x": 0.053321117208123936,
          "y": 0.8573116315480691,
          "z": 0.7106541966108043
        },
        "Ks": {
          "x": 0.2740056848145046,
          "y": 0.2740056848145046,
          "z": 0.2740056848145046
        },
        "reflectionIntensity": 0.0,
        "shininess": 10,
        "isTransparent": false,
        "refractionIntensity": 0.3,
        "refractionIndex": 1.5
      }
    },
    {
      "shape": {
        "CLASSNAME": "edu.cg.scene.objects.Sphere",
        "DATA": {
          "center": {
            "x": 2.0,
            "y": 0.0,
            "z": -3.0
          },
          "radius": 0.5
        }
      },
      "material": {
        "Ka": {
          "x": 0.44514197107583114,
          "y": 0.004385643734989619,
          "z": 0.4901556801393419
        },
        "Kd": {
          "x": 0.8902839421516623,
          "y": 0.008771287469979239,
          "z": 0.9803113602786838
        },
        "Ks": {
          "x": 1.0,
          "y": 1.0,
          "z": 1.0
        },
        "reflectionIntensity": 0.0,
        "shininess": 10,
        "isTransparent": true,
        "refractionIntensity": 1.0,
        "refractionIndex": 1.7663805621948545
      }
    },
    {
      "shape": {
        "CLASSNAME": "edu.cg.scene.objects.Sphere",
        "DATA": {
          "center": {
            "x": 3.0,
            "y": 0.0,
            "z": -3.0
          },
          "radius": 0.5
        }
      },
      "material": {
        "Ka": {
          "x": 0.49016631374854197,
          "y": 0.1756511642357334,
          "z": 0.22285905509663007
        },
        "Kd": {
          "x": 0.9803326274970839,
          "y": 0.3513023284714668,
          "z": 0.44571811019326013
        },
        "Ks": {
          "x": 0.7444239304865286,
          "y": 0.7444239304865286,
          "z": 0.7444239304865286
        },
        "reflectionIntensity": 0.9830745424854472,
        "shininess": 10,
        "isTransparent": true,
        "refractionIntensity": 0.34407273937264293,
        "refractionIndex": 1.7376055584650913
      }
    }
  ]
}